saturn_notebook/__init__.py
saturn_notebook/__main__.py
saturn_notebook/cells.py
saturn_notebook/evaluate.py
saturn_notebook/image.py
saturn_notebook/mpl.py
saturn_notebook/notebook.py
saturn_notebook/repl.py
saturn_notebook/theme.py
saturn_notebook/traceback.py
saturn_notebook/utils.py
saturn_notebook/viewer.py
saturn_notebook-1.3.0.dist-info/METADATA
saturn_notebook-1.3.0.dist-info/WHEEL
saturn_notebook-1.3.0.dist-info/entry_points.txt
saturn_notebook-1.3.0.dist-info/licenses/LICENSE.txt
saturn_notebook-1.3.0.dist-info/RECORD
