Metadata-Version: 2.4
Name: saturn-notebook
Version: 1.3.0
Summary: Plain-text Python notebooks with checkpointing
License-Expression: BSD-3-Clause-LBNL
License-File: LICENSE.txt
Requires-Python: >=3.8
Requires-Dist: argh==0.26.2
Requires-Dist: atomicwrites>=1.4.0
Requires-Dist: dill>=0.3.8
Requires-Dist: importlib-metadata>=4.11.3
Requires-Dist: markdown>=3.3.6
Requires-Dist: matplotlib>=3.5.0
Requires-Dist: more-itertools>=8.12.0
Requires-Dist: nbformat>=5.7.0
Requires-Dist: ptpython>=3.0.29
Requires-Dist: pygments>=2.18.0
Requires-Dist: rich>=12.3.0
Requires-Dist: wurlitzer>=3.0.2
Provides-Extra: viewer
Requires-Dist: appdirs>=1.4.4; extra == 'viewer'
Requires-Dist: pywebview>=3.3.1; extra == 'viewer'
